dpwagtail/__init__.py
dpwagtail/admin.py
dpwagtail/app_name.py
dpwagtail/dash_apps.py
dpwagtail/models.py
dpwagtail/urls.py
dpwagtail/utils.py
dpwagtail/version.py
dpwagtail/views.py
dpwagtail/management/commands/add_app_pages.py
dpwagtail/management/commands/add_initial_items.py
dpwagtail/migrations/0001_initial.py
dpwagtail/migrations/0002_djangoplotlydashindexpage.py
dpwagtail/migrations/0003_djangoplotlydashpage_short_description.py
dpwagtail/migrations/0004_djangoplotlydashblogpage_dashinstancesnippet.py
dpwagtail/migrations/__init__.py
dpwagtail/templates/dpwagtail/base.html
dpwagtail/templates/dpwagtail/django_plotly_dash_blog_page.html
dpwagtail/templates/dpwagtail/django_plotly_dash_index_page.html
dpwagtail/templates/dpwagtail/django_plotly_dash_page.html
dpwagtail/templates/dpwagtail/instancebuilder_list.html
dpwagtail/templates/dpwagtail/simple_django_plotly_dash_page.html
dpwagtail/templates/dpwagtail/tags/dpd_blog_block.html
dpwagtail/templates/dpwagtail/tags/dpd_blog_body.html
dpwagtail/templates/dpwagtail/tags/dpd_blog_page_short_listing.html
dpwagtail/templates/dpwagtail/tags/dpd_page_short_listing.html
dpwagtail/templates/dpwagtail/tags/dpw_instance.html
dpwagtail/templatetags/dpwagtail.py
django_plotly_wagtail-0.2.0.dist-info/METADATA
django_plotly_wagtail-0.2.0.dist-info/WHEEL
django_plotly_wagtail-0.2.0.dist-info/top_level.txt
django_plotly_wagtail-0.2.0.dist-info/RECORD
