Metadata-Version: 2.1
Name: django-plotly-wagtail
Version: 0.2.0
Summary: Django Wagtail use of django-plotly-dash and plotly dash
Home-page: https://gitlab.com/GibbsConsulting/django-plotly-wagtail
Author: Gibbs Consulting
Author-email: py.dpwagtail@gibbsconsulting.ca
License: AGPL v3
Project-URL: Source, https://gitlab.com/GibbsConsulting/django-plotly-wagtail
Project-URL: Tracker, https://gitlab.com/GibbsConsulting/django-plotly-wagtail/issues
Project-URL: Documentation, http://django-plotly-wagtail.readthedocs.io/
Keywords: django plotly plotly-dash dash dashboard wagtail
Classifier: Development Status :: 3 - Alpha
Classifier: Intended Audience :: Developers
Classifier: License :: OSI Approved :: GNU Affero General Public License v3
Classifier: Programming Language :: Python :: 3
Classifier: Framework :: Dash
Requires-Python: >=3.9
Requires-Dist: django>3.2
Requires-Dist: django-plotly-dash
Requires-Dist: wagtail
